<treatment><meta><source><author>Elvis Wu</author><date>2013</date><title>Elvis</title></source><processed_by><processor><date>Saturday, 2014 March 29 17:12:04 UTC-7</date><software type="Semantic Markup Input Generator" version="1.0"/><operator>elvis</operator></processor></processed_by></meta><taxon_identification status="ACCEPTED"><order_name>aaa</order_name><strain_name>1123</strain_name><strain_source>1212</strain_source></taxon_identification><description type="morphology">dasdsdasdasdasd</description></treatment>